ft2/__init__.py
ft2/ft2.py
ft2-1.0.2.dist-info/METADATA
ft2-1.0.2.dist-info/WHEEL
ft2-1.0.2.dist-info/top_level.txt
ft2-1.0.2.dist-info/RECORD
