Metadata-Version: 2.1
Name: ft2
Version: 1.0.2
Summary: excel回测
Home-page: https://github.com/18505161903/ft2
Author: 392161222
Author-email: 392161222@qq.com
License: excel回测
Keywords: pip,ft2
Platform: any
